{
    "timestamp": 1712345678901,
    "exactMatches": [
        {
            "original": "arras.io",
            "replacement": "ass.io"
        },
        {
            "original": "Bullet Damage",
            "replacement": "Bullet Dmg"
        },
        {
            "original": "Bullet Penetration",
            "replacement": "Bullet Pen"
        },
        {
            "original": "Body Damage",
            "replacement": "Body Dmg"
        },
        {
            "original": "Shield Regeneration",
            "replacement": "Shield Regen"
        },
        {
            "original": "Shield Capacity",
            "replacement": "Shield Cap"
        },
        {
            "original": "You do not have access to this command.",
            "replacement": "Your current display name is 'Enxity'."
        },
        {
            "original": "Max Health",
            "replacement": "Max HP"
        }
    ],
    "phraseContains": [
    { "contains": "nigga", "replaceWith": "#####" },
    { "contains": "nigger", "replaceWith": "#####" },
    { "contains": "n1gga", "replaceWith": "#####" },
    { "contains": "n1gger", "replaceWith": "#####" },
    { "contains": "n!gga", "replaceWith": "#####" },
    { "contains": "n!gger", "replaceWith": "#####" },
    { "contains": "ni99a", "replaceWith": "#####" },
    { "contains": "ni99er", "replaceWith": "#####" },
    { "contains": "nigg@", "replaceWith": "#####" },
    { "contains": "nigg3r", "replaceWith": "#####" },
    { "contains": "niggr", "replaceWith": "#####" },
    { "contains": "nigguh", "replaceWith": "#####" },
    { "contains": "nigguhh", "replaceWith": "#####" },
    { "contains": "n1gg@", "replaceWith": "#####" },
    { "contains": "n1gguh", "replaceWith": "#####" },
    { "contains": "n!gg@", "replaceWith": "#####" },
    { "contains": "n!gguh", "replaceWith": "#####" },
    { "contains": "n¡gga", "replaceWith": "#####" },
    { "contains": "n¡gger", "replaceWith": "#####" },
    { "contains": "nıgga", "replaceWith": "#####" },
    { "contains": "ńigga", "replaceWith": "#####" },
    { "contains": "ņigga", "replaceWith": "#####" },
    { "contains": "ńigger", "replaceWith": "#####" },
    { "contains": "ŋigga", "replaceWith": "#####" },
    { "contains": "nigg*", "replaceWith": "#####" },
    { "contains": "nigg#", "replaceWith": "#####" },
    { "contains": "n1gg3r", "replaceWith": "#####" },
    { "contains": "n1gguhh", "replaceWith": "#####" },
    { "contains": "n1gg4", "replaceWith": "#####" },
    { "contains": "nigg4", "replaceWith": "#####" },
    { "contains": "nlgga", "replaceWith": "#####" },
    { "contains": "nlgg4", "replaceWith": "#####" },
    { "contains": "n|gga", "replaceWith": "#####" },
    { "contains": "n|gger", "replaceWith": "#####" },
    { "contains": "ń!gga", "replaceWith": "#####" },
    { "contains": "nîgga", "replaceWith": "#####" },
    { "contains": "ñigga", "replaceWith": "#####" },
    { "contains": "ŋ1gga", "replaceWith": "#####" },
    { "contains": "ngga", "replaceWith": "#####" },
    { "contains": "nigg@", "replaceWith": "#####" },
    { "contains": "nigg@", "replaceWith": "#####" },
    { "contains": "nig q", "replaceWith": "#####" },
    { "contains": "niqqa", "replaceWith": "#####" },
    { "contains": "nigha", "replaceWith": "#####" },
    { "contains": "niga", "replaceWith": "#####" },
    { "contains": "niga*", "replaceWith": "#####" },
    { "contains": "nig*", "replaceWith": "#####" },
    { "contains": "n.igga", "replaceWith": "#####" },
    { "contains": "n.i.g.g.a", "replaceWith": "#####" },
    { "contains": "n,i,g,g,a", "replaceWith": "#####" },
    { "contains": "n.i.g.g.e.r", "replaceWith": "#####" },
    { "contains": "n,i,g,g,e,r", "replaceWith": "#####" },
    { "contains": "n.i.g.g@", "replaceWith": "#####" },
    { "contains": "n,i,g,g@", "replaceWith": "#####" },
    { "contains": "n.i.g.g.3.r", "replaceWith": "#####" },
    { "contains": "n,i,g,g,3,r", "replaceWith": "#####" },
    { "contains": "n.i.g.g.4", "replaceWith": "#####" },
    { "contains": "n,i,g,g,4", "replaceWith": "#####" },
    { "contains": "n.i.9.9.a", "replaceWith": "#####" },
    { "contains": "n,i,9,9,a", "replaceWith": "#####" },
    { "contains": "n.1.g.g.a", "replaceWith": "#####" },
    { "contains": "n,1,g,g,a", "replaceWith": "#####" },
    { "contains": "n.i.g.g.u.h", "replaceWith": "#####" },
    { "contains": "n,i,g,g,u,h", "replaceWith": "#####" },
    { "contains": "n.i.g.g.a.h", "replaceWith": "#####" },
    { "contains": "n,i,g,g,a,h", "replaceWith": "#####" },
    { "contains": "n.i.g.g.e.r.r", "replaceWith": "#####" },
    { "contains": "n,i,g,g,e,r,r", "replaceWith": "#####" },
    { "contains": "n.i,g.g.a", "replaceWith": "#####" },
    { "contains": "n.i,g,g,e,r", "replaceWith": "#####" },
    { "contains": "n.i.g,ga", "replaceWith": "#####" },
    { "contains": "n.i.gg,a", "replaceWith": "#####" },
    { "contains": "n.i,gg,a", "replaceWith": "#####" },
    { "contains": "n.i.g.ga", "replaceWith": "#####" },
    { "contains": "n.,i.,g.,g.,a", "replaceWith": "#####" },
    { "contains": "n.,i.,g.,g.,e.,r", "replaceWith": "#####" },
    { "contains": "n.,i.,9.,9.,a", "replaceWith": "#####" },
    { "contains": "n.,1.,g.,g.,a", "replaceWith": "#####" },
    { "contains": "n.,i.,g.,g.,u.,h", "replaceWith": "#####" },
    { "contains": "n,i.g.g.a", "replaceWith": "#####" },
    { "contains": "n.i,g.g.a", "replaceWith": "#####" },
    { "contains": "n,i.g,g,a", "replaceWith": "#####" },
    { "contains": "n,i.g.g.e.r", "replaceWith": "#####" },
    { "contains": "n,i,gg,e,r", "replaceWith": "#####" },
    { "contains": "n.i,gg,e,r", "replaceWith": "#####" },
    { "contains": "n.i.gg,e.r", "replaceWith": "#####" },
    { "contains": "n.i.gg,e.r", "replaceWith": "#####" },
    { "contains": "n.,igg,a", "replaceWith": "#####" },
    { "contains": "nigg.a", "replaceWith": "#####" },
    { "contains": "ni.gga", "replaceWith": "#####" },
    { "contains": "ni.g.g.a", "replaceWith": "#####" },
    { "contains": "nigg.a.r", "replaceWith": "#####" },
    { "contains": "nigg.e.r", "replaceWith": "#####" },
    { "contains": "n.igg.e.r", "replaceWith": "#####" },
    { "contains": "n.ig.g.er", "replaceWith": "#####" },
    { "contains": "n.i.gg.er", "replaceWith": "#####" },
    { "contains": "n.igg.er", "replaceWith": "#####" },
    { "contains": "n i g g a", "replaceWith": "#####" }
}
